LICENSE
MANIFEST.in
README
setup.cfg
setup.py
setup_helper.py
test.py
demos/demo.py
demos/demo_server.py
demos/demo_sftp.py
demos/demo_simple.py
demos/forward.py
demos/interactive.py
demos/rforward.py
demos/test_rsa.key
demos/user_rsa_key
demos/user_rsa_key.pub
paramiko/__init__.py
paramiko/agent.py
paramiko/auth_handler.py
paramiko/ber.py
paramiko/buffered_pipe.py
paramiko/channel.py
paramiko/client.py
paramiko/common.py
paramiko/compress.py
paramiko/config.py
paramiko/dsskey.py
paramiko/file.py
paramiko/hostkeys.py
paramiko/kex_gex.py
paramiko/kex_group1.py
paramiko/logging22.py
paramiko/message.py
paramiko/packet.py
paramiko/pipe.py
paramiko/pkey.py
paramiko/primes.py
paramiko/resource.py
paramiko/rng.py
paramiko/rng_posix.py
paramiko/rng_win32.py
paramiko/rsakey.py
paramiko/server.py
paramiko/sftp.py
paramiko/sftp_attr.py
paramiko/sftp_client.py
paramiko/sftp_file.py
paramiko/sftp_handle.py
paramiko/sftp_server.py
paramiko/sftp_si.py
paramiko/ssh_exception.py
paramiko/transport.py
paramiko/util.py
paramiko/win_pageant.py
paramiko_on_pypi.egg-info/PKG-INFO
paramiko_on_pypi.egg-info/SOURCES.txt
paramiko_on_pypi.egg-info/dependency_links.txt
paramiko_on_pypi.egg-info/requires.txt
paramiko_on_pypi.egg-info/top_level.txt
tests/loop.py
tests/stub_sftp.py
tests/test_auth.py
tests/test_buffered_pipe.py
tests/test_client.py
tests/test_dss.key
tests/test_dss_password.key
tests/test_file.py
tests/test_hostkeys.py
tests/test_kex.py
tests/test_message.py
tests/test_packetizer.py
tests/test_pkey.py
tests/test_rsa.key
tests/test_rsa_password.key
tests/test_sftp.py
tests/test_sftp_big.py
tests/test_transport.py
tests/test_util.py