Metadata-Version: 1.0
Name: paramiko-on-pypi
Version: 1.7.6
Summary: SSH2 protocol library
Home-page: http://www.lag.net/paramiko/
Author: Robey Pointer
Author-email: robeypointer@gmail.com
License: LGPL
Platform: Posix; MacOS X; Windows
Classifier: Development Status :: 5 - Production/Stable
Classifier: Intended Audience :: Developers
Classifier: License :: OSI Approved :: GNU Library or Lesser General Public License (LGPL)
Classifier: Operating System :: OS Independent
Classifier: Topic :: Internet
Classifier: Topic :: Security :: Cryptography
